fastcommand/__init__.py
fastcommand/main.py
fastcommand-0.1.8.dist-info/LICENSE
fastcommand-0.1.8.dist-info/METADATA
fastcommand-0.1.8.dist-info/WHEEL
fastcommand-0.1.8.dist-info/top_level.txt
fastcommand-0.1.8.dist-info/RECORD
