Metadata-Version: 2.1
Name: fastcommand
Version: 0.1.8
Author-email: Jason Morley <hello@jbmorley.co.uk>
License: MIT License
License-File: LICENSE
